pynncml/__init__.py
pynncml/plot_common.py
pynncml/utils.py
pynncml/datasets/__init__.py
pynncml/datasets/base_rain_sensors.py
pynncml/datasets/dataset.py
pynncml/datasets/gauge_data.py
pynncml/datasets/link_data.py
pynncml/datasets/link_processing.py
pynncml/datasets/loaders.py
pynncml/datasets/meta_data.py
pynncml/datasets/radar_data.py
pynncml/datasets/sensors_set.py
pynncml/datasets/xarray_processing.py
pynncml/metrics/__init__.py
pynncml/metrics/classification.py
pynncml/metrics/regression.py
pynncml/metrics/results_accumlator.py
pynncml/model_zoo/__init__.py
pynncml/model_zoo/model_common.py
pynncml/model_zoo/one_step_1_rnntype_best.gru
pynncml/model_zoo/one_step_1_rnntype_best.lstm
pynncml/model_zoo/one_step_2_rnntype_best.gru
pynncml/model_zoo/one_step_2_rnntype_best.lstm
pynncml/model_zoo/one_step_3_rnntype_best.gru
pynncml/model_zoo/one_step_3_rnntype_best.lstm
pynncml/model_zoo/two_step_1_rnntype_best.gru
pynncml/model_zoo/two_step_1_rnntype_best.lstm
pynncml/model_zoo/two_step_2_rnntype_best.gru
pynncml/model_zoo/two_step_2_rnntype_best.lstm
pynncml/model_zoo/two_step_3_rnntype_best.gru
pynncml/model_zoo/two_step_3_rnntype_best.lstm
pynncml/model_zoo/wet_dry_1_rnntype_best.gru
pynncml/model_zoo/wet_dry_1_rnntype_best.lstm
pynncml/model_zoo/wet_dry_2_rnntype_best.gru
pynncml/model_zoo/wet_dry_2_rnntype_best.lstm
pynncml/model_zoo/wet_dry_3_rnntype_best.gru
pynncml/model_zoo/wet_dry_3_rnntype_best.lstm
pynncml/multiple_cmls_methods/__init__.py
pynncml/multiple_cmls_methods/infer_multiple_cmls.py
pynncml/multiple_cmls_methods/rain_field_reconstruction/__init__.py
pynncml/multiple_cmls_methods/rain_field_reconstruction/gmz.py
pynncml/multiple_cmls_methods/rain_field_reconstruction/idw.py
pynncml/neural_networks/__init__.py
pynncml/neural_networks/backbone.py
pynncml/neural_networks/nn_config.py
pynncml/neural_networks/normalization.py
pynncml/neural_networks/rain_gan.py
pynncml/neural_networks/rain_head.py
pynncml/neural_networks/tn_layer.py
pynncml-0.3.7.dist-info/LICENSE
pynncml-0.3.7.dist-info/METADATA
pynncml-0.3.7.dist-info/WHEEL
pynncml-0.3.7.dist-info/top_level.txt
pynncml-0.3.7.dist-info/RECORD
