Metadata-Version: 2.1
Name: pynncml
Version: 0.3.7
Summary: A python toolbox based on PyTorch which utilized neural network for rain estimation and classification from commercial microwave link (CMLs) data.
Home-page: https://github.com/haihabi/pynncml
Author: Hai Victor Habi
Author-email: victoropensource@gmail.com
Classifier: Programming Language :: Python :: 3
Classifier: License :: OSI Approved :: MIT License
Classifier: Operating System :: OS Independent
Requires-Python: >=3.9
License-File: LICENSE
Requires-Dist: numpy
Requires-Dist: torch
Requires-Dist: torchvision
Requires-Dist: matplotlib
Requires-Dist: scipy
Requires-Dist: pandas
Requires-Dist: xarray
Requires-Dist: utm
Requires-Dist: netcdf4
Requires-Dist: tqdm
Requires-Dist: prettytable
Requires-Dist: huggingface-hub
